commit_bot/__init__.py
commit_bot/ai_models.py
commit_bot/huggingface_chat_model.py
commit_bot/main.py
commit_bot/prompts.py
commit_bot/utils.py
commit_bot/bin/exec_vllm.sh
commit_bot/bin/stop_vllm.sh
commit_bot/bin/vllm_utils.sh
commit_bot/conf/README.md
commit_bot/conf/job.conf
commit_bot/conf/model.conf
commit_bot/var/logs/.keep
commit_bot-1.1.8.dist-info/licenses/LICENSE
commit_bot-1.1.8.dist-info/METADATA
commit_bot-1.1.8.dist-info/WHEEL
commit_bot-1.1.8.dist-info/entry_points.txt
commit_bot-1.1.8.dist-info/top_level.txt
commit_bot-1.1.8.dist-info/RECORD
