Metadata-Version: 2.4
Name: commit-bot
Version: 1.1.8
Summary: A brief description of your project.
Classifier: Programming Language :: Python :: 3
Classifier: License :: OSI Approved :: MIT License
Classifier: Operating System :: OS Independent
Requires-Python: <=3.13.9,>=3.10
License-File: LICENSE
Requires-Dist: pyhocon==0.3.61
Requires-Dist: litellm==1.76.3
Requires-Dist: vllm==0.10.2
Provides-Extra: dev
Requires-Dist: pytest; extra == "dev"
Requires-Dist: pytest-cov; extra == "dev"
Requires-Dist: jupyterlab; extra == "dev"
Requires-Dist: jupyterlab-vim; extra == "dev"
Requires-Dist: ipython; extra == "dev"
Requires-Dist: python-lsp-server[all]; extra == "dev"
Requires-Dist: pylint; extra == "dev"
Requires-Dist: flake8; extra == "dev"
Requires-Dist: flake8-quotes; extra == "dev"
Requires-Dist: pep8-naming; extra == "dev"
Requires-Dist: isort; extra == "dev"
Requires-Dist: openpyxl; extra == "dev"
Requires-Dist: visidata; extra == "dev"
Requires-Dist: csvkit; extra == "dev"
Requires-Dist: black; extra == "dev"
Requires-Dist: tabulate[widechars]; extra == "dev"
Requires-Dist: build; extra == "dev"
Requires-Dist: twine; extra == "dev"
Dynamic: license-file
